FNTwitchSetup/__init__.py
FNTwitchSetup/get_cosmetic.py
FNTwitchSetup/glitch.py
FNTwitchSetup/utils.py
FNTwitchSetup/events/__init__.py
FNTwitchSetup/events/friends.py
FNTwitchSetup/events/message.py
FNTwitchSetup/events/party.py
FNTwitchSetup/events/ready.py
FNTwitchSetup-1.0.1.dist-info/METADATA
FNTwitchSetup-1.0.1.dist-info/WHEEL
FNTwitchSetup-1.0.1.dist-info/top_level.txt
FNTwitchSetup-1.0.1.dist-info/RECORD
